beppu/__init__.py
beppu-0.0.1.dist-info/METADATA
beppu-0.0.1.dist-info/WHEEL
beppu-0.0.1.dist-info/top_level.txt
beppu-0.0.1.dist-info/RECORD
