Metadata-Version: 2.1
Name: beppu
Version: 0.0.1
Summary: Enum based asyncio synchronization event wrapper
Home-page: https://github.com/ashwoods/beppu
Author: Ashley Camba Garrido
Author-email: ashwoods@gmail.com
License: MIT
Platform: UNKNOWN
Classifier: Development Status :: 2 - Pre-Alpha
Classifier: Intended Audience :: Developers
Classifier: License :: OSI Approved :: MIT License
Classifier: Operating System :: OS Independent
Classifier: Programming Language :: Python
Classifier: Programming Language :: Python :: 3.6
Classifier: Programming Language :: Python :: 3.7
Classifier: Programming Language :: Python :: 3.8
Classifier: Topic :: Software Development :: Libraries :: Python Modules
Provides-Extra: test
Requires-Dist: colorlog ; extra == 'test'
Requires-Dist: pytest ; extra == 'test'
Requires-Dist: pytest-cov ; extra == 'test'
Requires-Dist: pytest-flake8 ; extra == 'test'
Requires-Dist: flake8-bugbear ; extra == 'test'
Requires-Dist: flake8-import-order ; extra == 'test'
Requires-Dist: pytest-black ; extra == 'test'
Requires-Dist: pytest-asyncio ; extra == 'test'
Requires-Dist: pytest-bandit ; extra == 'test'
Requires-Dist: pytest-benchmark ; extra == 'test'
Requires-Dist: pytest-profiling ; extra == 'test'
Requires-Dist: pytest-leaks ; extra == 'test'
Requires-Dist: memory-profiler ; extra == 'test'
Requires-Dist: pytest-xdist ; extra == 'test'
Requires-Dist: pdbpp ; extra == 'test'
